Metadata-Version: 2.1
Name: pyclone-module
Version: 1.53.1
Summary: Python interface for rclone
Home-page: https://github.com/Mwimwii/pyclone
Author: Mwila Nyirongo
Author-email: mpnyirongo@gmail.com
License: MIT license
Keywords: pyclone
Platform: UNKNOWN
Classifier: Development Status :: 4 - Beta
Classifier: Intended Audience :: Developers
Classifier: License :: OSI Approved :: MIT License
Classifier: Natural Language :: English
Classifier: Programming Language :: Python :: 3
Classifier: Programming Language :: Python :: 3.5
Classifier: Programming Language :: Python :: 3.6
Classifier: Programming Language :: Python :: 3.7
Classifier: Programming Language :: Python :: 3.8
Classifier: Operating System :: MacOS :: MacOS X
Classifier: Operating System :: Microsoft :: Windows
Classifier: Operating System :: POSIX :: SunOS/Solaris
Classifier: Operating System :: Unix
Classifier: Topic :: Communications :: File Sharing
Classifier: Topic :: Internet
Classifier: Topic :: Utilities
Requires-Python: >=3.2
Provides-Extra: dev
